mezzanine_shortcodes-0.2.2.dist-info/DESCRIPTION.rst
mezzanine_shortcodes-0.2.2.dist-info/top_level.txt
mezzanine_shortcodes-0.2.2.dist-info/RECORD
mezzanine_shortcodes-0.2.2.dist-info/WHEEL
mezzanine_shortcodes-0.2.2.dist-info/METADATA
mezzanine_shortcodes-0.2.2.dist-info/metadata.json
shortcodes/register_api.py
shortcodes/forms.py
shortcodes/__init__.py
shortcodes/signals.py
shortcodes/defaults.py
shortcodes/state.py
shortcodes/register.py
shortcodes/utils.py
shortcodes/views.py
shortcodes/apps.py
shortcodes/render.py
shortcodes/urls.py
shortcodes/static/shortcodes/dialog.css
shortcodes/static/shortcodes/insert_shortcode.js
shortcodes/static/shortcodes/tinymce/plugin.js
shortcodes/static/shortcodes/tinymce/style.css
shortcodes/templates/shortcodes/dialog.html
example_project/__init__.py
example_project/manage.py
example_project/.gitignore
example_project/example_app/__init__.py
example_project/example_app/shortcodes.py
example_project/example_app/models.py
example_project/example_app/static/js/tinymce_setup.js
example_project/example_app/static/img/audio.png
example_project/example_app/templates/person.html
example_project/project/__init__.py
example_project/project/wsgi.py
example_project/project/settings.py
example_project/project/dev_settings.py
example_project/project/urls.py
